zip2zip/__init__.py
zip2zip/codebook.py
zip2zip/config.py
zip2zip/constants.py
zip2zip/logging_utils.py
zip2zip/model.py
zip2zip/tokenizer.py
zip2zip/utils.py
zip2zip/visual.py
zip2zip/nn/__init__.py
zip2zip/nn/embedding.py
zip2zip/nn/linear.py
zip2zip/nn/encoders/__init__.py
zip2zip/nn/encoders/attention.py
zip2zip/nn/encoders/base.py
zip2zip/nn/encoders/config.py
zip2zip/nn/encoders/transformer.py
zip2zip/tools/token_efficiency_calc.py
zip2zip-0.1.2.dist-info/licenses/LICENSE
zip2zip-0.1.2.dist-info/METADATA
zip2zip-0.1.2.dist-info/WHEEL
zip2zip-0.1.2.dist-info/top_level.txt
zip2zip-0.1.2.dist-info/RECORD
