Metadata-Version: 2.4
Name: zip2zip
Version: 0.1.2
Summary: Inference-time adaptive token vocabularies for LLMs
Author-email: EPFL-DLAB <saibo.geng@epfl.ch>
License:                                  Apache License
Project-URL: Homepage, https://github.com/epfl-dlab/zip2zip
Requires-Python: >=3.10
License-File: LICENSE
Requires-Dist: zip2zip-compression>=0.3.3
Requires-Dist: torch>=2.5.0
Requires-Dist: datasets<=3.1.0
Requires-Dist: transformers>=4.47.0
Requires-Dist: omegaconf>=2.3.0
Requires-Dist: accelerate>=0.32.0
Requires-Dist: peft>=0.14.0
Requires-Dist: pytest
Dynamic: license-file
